{
  "commit": "54b43e11a772b9c83d2a7726ed6ef92a183cc758",
  "generated": "Sat, 11 May 2024 05:20:40 GMT",
  "metadata": [
    {
      "__outstatic": {
        "commit": "1aae964766343e4fc17ca561060fef25baf08b8c",
        "hash": "2410130508",
        "path": "/outstatic/content/users/this-is-test.md"
      },
      "author": {
        "name": "Hem",
        "picture": "https://avatars.githubusercontent.com/u/112458846?v=4"
      },
      "collection": "users",
      "coverImage": "/images/cat-M1Mj.png",
      "description": "this is descripiton ",
      "publishedAt": "2024-05-11T05:47:04.781Z",
      "slug": "this-is-test",
      "status": "draft",
      "title": "This is test"
    }
  ]
}